{
  "projects": [],
  "goals": [
    {
      "goalName": "First Goal",
      "Estimatedhours": "2",
      "startDate": "2023-09-18T18:30:00.000Z",
      "endDate": "2023-09-28T18:30:00.000Z",
      "description": "First GoalFirst GoalFirst GoalFirst GoalFirst GoalFirst GoalFirst Goal",
      "id": 1
    },
    {
      "goalName": "2 nd goal",
      "Estimatedhours": "3",
      "startDate": "2023-09-19T18:30:00.000Z",
      "endDate": "2023-09-22T18:30:00.000Z",
      "description": "xxxxxxxxxxxxxxxxxxxxxssssssssssssssssssssss",
      "id": 2
    }
  ]
}